cyberfusion/ExternalProvidersIPRanges/__init__.py
python3_cyberfusion_external_providers_ip_ranges-2.4.dist-info/METADATA
python3_cyberfusion_external_providers_ip_ranges-2.4.dist-info/WHEEL
python3_cyberfusion_external_providers_ip_ranges-2.4.dist-info/entry_points.txt
python3_cyberfusion_external_providers_ip_ranges-2.4.dist-info/top_level.txt
python3_cyberfusion_external_providers_ip_ranges-2.4.dist-info/RECORD
