Metadata-Version: 2.4
Name: python3-cyberfusion-external-providers-ip-ranges
Version: 2.4
Summary: Scripts to add IP ranges of external providers to ferm.
Author-email: Cyberfusion <support@cyberfusion.io>
Project-URL: Source, https://github.com/CyberfusionIO/python3-cyberfusion-external-providers-ip-ranges
Requires-Dist: requests==2.32.3
Requires-Dist: python3-cyberfusion-common~=2.12
Requires-Dist: python3-cyberfusion-ferm-support~=1.3
